Metadata-Version: 2.1
Name: typebuild
Version: 0.0.32
Summary: A brief description of your package
Home-page: https://github.com/project-typebuild/typebuild
Author: iRanadheer
Author-email: neneranadheer@gmail.com
Classifier: Development Status :: 3 - Alpha
Classifier: Intended Audience :: Developers
Classifier: License :: Other/Proprietary License
Classifier: Programming Language :: Python :: 3
Classifier: Programming Language :: Python :: 3.6
Classifier: Programming Language :: Python :: 3.7
Classifier: Programming Language :: Python :: 3.8
Classifier: Programming Language :: Python :: 3.9
Classifier: Programming Language :: Python :: 3.10
License-File: LICENSE
Requires-Dist: anthropic
Requires-Dist: chardet
Requires-Dist: dataclasses-json
Requires-Dist: extra-streamlit-components
Requires-Dist: faker-commerce
Requires-Dist: fsspec
Requires-Dist: googlesearch-python
Requires-Dist: google-api-python-client
Requires-Dist: hydralit-components
Requires-Dist: isodate
Requires-Dist: numexpr
Requires-Dist: nx-altair
Requires-Dist: openai
Requires-Dist: openpyxl
Requires-Dist: pip-chill
Requires-Dist: pympler
Requires-Dist: sqlalchemy
Requires-Dist: stqdm
Requires-Dist: streamlit-ace
Requires-Dist: streamlit-datalist
Requires-Dist: streamlit-extras
Requires-Dist: streamlit-option-menu
Requires-Dist: streamlit-pandas-profiling
Requires-Dist: tabulate
Requires-Dist: threadpoolctl
Requires-Dist: tiktoken
Requires-Dist: tldextract
Requires-Dist: youtube-search
Requires-Dist: youtube-transcript-api
Requires-Dist: xlsxwriter
